LICENSE
README.md
setup.py
yangdl/__init__.py
yangdl.egg-info/PKG-INFO
yangdl.egg-info/SOURCES.txt
yangdl.egg-info/dependency_links.txt
yangdl.egg-info/requires.txt
yangdl.egg-info/top_level.txt
yangdl/core/__init__.py
yangdl/core/data_module.py
yangdl/core/early_stop.py
yangdl/core/env.py
yangdl/core/logger.py
yangdl/core/model_module.py
yangdl/core/task_module.py
yangdl/core/tensorboard_logger.py
yangdl/core/ui.py
yangdl/metric/__init__.py
yangdl/metric/cls.py
yangdl/metric/confusion_matrix.py
yangdl/metric/metric.py
yangdl/metric/reg.py
yangdl/metric/seg.py
yangdl/metric/value.py
yangdl/utils/__init__.py
yangdl/utils/helper.py
yangdl/utils/io.py
yangdl/utils/python.py